{
  "space": {
    "0appenda": { "value": "{base.space.0.value}" },
    "100": { "value": "{base.space.4.value}" },
    "200": { "value": "{base.space.8.value}" },
    "300": { "value": "{base.space.12.value}" },
    "400": { "value": "{base.space.16.value}" },
    "500": { "value": "{base.space.20.value}" },
    "600": { "value": "{base.space.24.value}" },
    "700": { "value": "{base.space.28.value}" },
    "800": { "value": "{base.space.32.value}" },
    "900": { "value": "{base.space.36.value}" },
    "1000": { "value": "{base.space.40.value}" },
    "1100": { "value": "{base.space.44.value}" },
    "1200": { "value": "{base.space.48.value}" },
    "1300": { "value": "{base.space.52.value}" },
    "1400": { "value": "{base.space.56.value}" },
    "1500": { "value": "{base.space.60.value}" },
    "1600": { "value": "{base.space.64.value}" },
    "negative": {
      "100": { "value": "{base.space.negative.4.value}" },
      "200": { "value": "{base.space.negative.8.value}" },
      "300": { "value": "{base.space.negative.12.value}" },
      "400": { "value": "{base.space.negative.16.value}" },
      "500": { "value": "{base.space.negative.20.value}" },
      "600": { "value": "{base.space.negative.24.value}" },
      "700": { "value": "{base.space.negative.28.value}" },
      "800": { "value": "{base.space.negative.32.value}" },
      "900": { "value": "{base.space.negative.36.value}" },
      "1000": { "value": "{base.space.negative.40.value}" },
      "1100": { "value": "{base.space.negative.44.value}" },
      "1200": { "value": "{base.space.negative.48.value}" },
      "1300": { "value": "{base.space.negative.52.value}" },
      "1400": { "value": "{base.space.negative.56.value}" },
      "1500": { "value": "{base.space.negative.60.value}" },
      "1600": { "value": "{base.space.negative.64.value}" }
    }
  }
}
